opencone/__init__.py
opencone/opencone.py
opencone-0.0.4.dist-info/METADATA
opencone-0.0.4.dist-info/WHEEL
opencone-0.0.4.dist-info/licenses/LICENSE
opencone-0.0.4.dist-info/RECORD
