Metadata-Version: 2.1
Name: opencone
Version: 0.0.4
Summary: A vector database wrapper on OpenSearch backend. [An alternative to Pinecone]
Project-URL: Homepage, https://github.com/mjdileep/Opencone
Project-URL: Bug Tracker, https://github.com/mjdileep/Opencone/issues
Author-email: Dileep Jayamal <dileep.jayamal@gmail.com>
License-File: LICENSE
Classifier: License :: OSI Approved :: MIT License
Classifier: Operating System :: OS Independent
Classifier: Programming Language :: Python :: 3
Requires-Python: >=3.7
